<?xml version="1.0" encoding="UTF-8"?>
<!DOCTYPE partida SYSTEM "ej4_3senraya.dtd">
<partida>
    <jugadores>
        <jugador id="j1">
            <nombre>Jose Vivo</nombre>
            <ficha>X</ficha>
        </jugador>
        <jugador id="j2">
            <nombre>Guillermo Santos</nombre>
            <ficha>O</ficha>
        </jugador>
    </jugadores>
    <turnos>
        <turno numero="1">
            <jugador>Jose Vivo</jugador>
            <posicion>3</posicion>
        </turno>
        <turno numero="2">
            <jugador>Guillermo Santos</jugador>
            <posicion>5</posicion>
        </turno>
        <turno numero="3">
            <jugador>Jose Vivo</jugador>
            <posicion>1</posicion>
        </turno>
        <turno numero="4">
            <jugador>Guillermo Santos</jugador>
            <posicion>4</posicion>
        </turno>
    </turnos>
</partida>
